pycolorname/VERSION
pycolorname/__init__.py
pycolorname/color_system.py
pycolorname/utilities.py
pycolorname/data/pycolorname.pantone.cal_print.json
pycolorname/data/pycolorname.pantone.logodesignteam.json
pycolorname/data/pycolorname.pantone.pantonepaint.json
pycolorname/data/pycolorname.ral.classic.ralcolor.json
pycolorname/data/pycolorname.ral.classic.wikipedia.json
pycolorname/pantone/__init__.py
pycolorname/pantone/cal_print.py
pycolorname/pantone/logodesignteam.py
pycolorname/pantone/pantonepaint.py
pycolorname/ral/__init__.py
pycolorname/ral/classic/__init__.py
pycolorname/ral/classic/ralcolor.py
pycolorname/ral/classic/wikipedia.py
pycolorname-0.1.0.dist-info/DESCRIPTION.rst
pycolorname-0.1.0.dist-info/METADATA
pycolorname-0.1.0.dist-info/RECORD
pycolorname-0.1.0.dist-info/WHEEL
pycolorname-0.1.0.dist-info/metadata.json
pycolorname-0.1.0.dist-info/top_level.txt
