Metadata-Version: 2.0
Name: pycolorname
Version: 0.1.0
Summary: Provides common color systems.
Home-page: https://github.com/AbdealiJK/pycolorname
Author: AbdealiJK
Author-email: abdealikothari@gmail.com
License: MIT
Platform: any
Classifier: Development Status :: 4 - Beta
Classifier: Environment :: Console
Classifier: Environment :: MacOS X
Classifier: Environment :: Win32 (MS Windows)
Classifier: Intended Audience :: Developers
Classifier: Operating System :: OS Independent
Classifier: Programming Language :: Python :: Implementation :: CPython
Requires-Dist: beautifulsoup4 (>=4.4.1)
Requires-Dist: colormath (>=2.1.1)
Requires-Dist: cssutils (>=1.0.1)
Requires-Dist: requests (>=2.9.1)
Requires-Dist: setuptools (>=19.2)
